powerapi/__init__.py
powerapi/exception.py
powerapi/message.py
powerapi/actor/__init__.py
powerapi/actor/actor.py
powerapi/actor/socket_interface.py
powerapi/actor/state.py
powerapi/actor/supervisor.py
powerapi/backend_supervisor/__init__.py
powerapi/backend_supervisor/backend_supervisor.py
powerapi/cli/__init__.py
powerapi/cli/binding_manager.py
powerapi/cli/common_cli_parsing_manager.py
powerapi/cli/config_parser.py
powerapi/cli/config_validator.py
powerapi/cli/generator.py
powerapi/cli/parsing_manager.py
powerapi/database/__init__.py
powerapi/database/base_db.py
powerapi/database/csv/__init__.py
powerapi/database/csv/csvdb.py
powerapi/database/file/__init__.py
powerapi/database/file/file_db.py
powerapi/database/influxdb2/__init__.py
powerapi/database/influxdb2/influxdb2.py
powerapi/database/mongodb/__init__.py
powerapi/database/mongodb/mongodb.py
powerapi/database/opentsdb/__init__.py
powerapi/database/opentsdb/opentsdb.py
powerapi/database/prometheus/__init__.py
powerapi/database/prometheus/prometheus_db.py
powerapi/database/socket/__init__.py
powerapi/database/socket/socket_db.py
powerapi/database/virtiofs/__init__.py
powerapi/database/virtiofs/virtiofs_db.py
powerapi/dispatch_rule/__init__.py
powerapi/dispatch_rule/dispatch_rule.py
powerapi/dispatch_rule/hwpc_dispatch_rule.py
powerapi/dispatch_rule/power_dispatch_rule.py
powerapi/dispatch_rule/procfs_dispatch_rule.py
powerapi/dispatcher/__init__.py
powerapi/dispatcher/blocking_detector.py
powerapi/dispatcher/dispatcher_actor.py
powerapi/dispatcher/handlers.py
powerapi/dispatcher/route_table.py
powerapi/filter/__init__.py
powerapi/filter/filter.py
powerapi/formula/__init__.py
powerapi/formula/abstract_cpu_dram_formula.py
powerapi/formula/formula_actor.py
powerapi/formula/handlers.py
powerapi/handler/__init__.py
powerapi/handler/handler.py
powerapi/handler/poison_pill_message_handler.py
powerapi/handler/start_handler.py
powerapi/processor/__init__.py
powerapi/processor/handlers.py
powerapi-2.10.0.dist-info/licenses/LICENSE
powerapi-2.10.0.dist-info/METADATA
powerapi-2.10.0.dist-info/WHEEL
powerapi-2.10.0.dist-info/top_level.txt
powerapi-2.10.0.dist-info/RECORD
