Metadata-Version: 2.4
Name: powerapi
Version: 2.10.0
Summary: PowerAPI is a middleware toolkit for building software-defined power meters.
Author-email: PowerAPI Staff <powerapi-staff@inria.fr>
License: BSD-3-Clause
Project-URL: homepage, https://powerapi.org
Project-URL: documentation, https://powerapi.readthedocs.org
Project-URL: repository, https://github.com/powerapi-ng/powerapi
Keywords: powerapi,energy,power-meter,green-computing
Classifier: Programming Language :: Python :: 3.10
Classifier: Programming Language :: Python :: 3.11
Classifier: Programming Language :: Python :: 3.12
Classifier: Programming Language :: Python :: 3.13
Classifier: License :: OSI Approved :: BSD License
Classifier: Intended Audience :: Science/Research
Classifier: Intended Audience :: Developers
Classifier: Development Status :: 5 - Production/Stable
Classifier: Topic :: Software Development :: Libraries :: Python Modules
Requires-Python: >=3.10
License-File: LICENSE
Requires-Dist: pyzmq>=18.1.0
Requires-Dist: setproctitle>=1.1.8
Provides-Extra: mongodb
Requires-Dist: pymongo>=3.7.2; extra == "mongodb"
Provides-Extra: influxdb
Requires-Dist: influxdb-client>=1.30.0; extra == "influxdb"
Provides-Extra: opentsdb
Requires-Dist: opentsdb-py>=0.6.0; extra == "opentsdb"
Provides-Extra: prometheus
Requires-Dist: prometheus-client>=0.9.0; extra == "prometheus"
Provides-Extra: kubernetes
Requires-Dist: kubernetes>=27.0.2; extra == "kubernetes"
Provides-Extra: all-databases
Requires-Dist: powerapi[influxdb,mongodb,opentsdb,prometheus]; extra == "all-databases"
Provides-Extra: all-platforms
Requires-Dist: powerapi[kubernetes]; extra == "all-platforms"
Provides-Extra: everything
Requires-Dist: powerapi[all-databases,all-platforms]; extra == "everything"
Dynamic: license-file
